[
  {
    "Symbol": "AIT",
    "Name": "Applied Industrial Technologies",
    "Exchange": "NYSE",
    "Last": 104.015,
    "Industry": "Machinery - General Industrial",
    "SIC Description": "SIC-5080 Wholesale-Machinery, Equipment & Supplies",
    "Time": "10:19 ET",
    "Div Payout%": "22.85%",
    "5Y Div%": "18.18%",
    "Cash Flow %(q)": "+67.06%",
    "Cash Flow %(a)": "-18.54%",
    "Signal": "Buy",
    "Direction": "Average",
    "1M High Date": "2022-04-29"
  },
  {
    "Symbol": "CHMG",
    "Name": "Chemung Financial Cp",
    "Exchange": "NASDAQ",
    "Last": 47.48,
    "Industry": "Banks - Southeast",
    "SIC Description": "SIC-6022 State Commercial Banks",
    "Time": "2022-04-29",
    "Div Payout%": "21.67%",
    "5Y Div%": "14.42%",
    "Cash Flow %(q)": "+33.41%",
    "Cash Flow %(a)": "+23.73%",
    "Signal": "Buy",
    "Direction": "Top 1%",
    "1M High Date": "2022-04-25"
  },
  {
    "Symbol": "CPB",
    "Name": "Campbell Soup Company",
    "Exchange": "NYSE",
    "Last": 47.41,
    "Industry": "Food - Misc & Diversified",
    "SIC Description": "SIC-2000 Food and Kindred Products",
    "Time": "10:35 ET",
    "Div Payout%": "54.65%",
    "5Y Div%": "16.80%",
    "Cash Flow %(q)": "+165.97%",
    "Cash Flow %(a)": "-25.86%",
    "Signal": "Buy",
    "Direction": "Strongest",
    "1M High Date": "2022-04-29"
  },
  {
    "Symbol": "CVLY",
    "Name": "Codorus Valley Bncp",
    "Exchange": "NASDAQ",
    "Last": 23.9,
    "Industry": "Banks - Northeast",
    "SIC Description": "SIC-6035 Savings Institution, Federally Chartered",
    "Time": "2022-04-29",
    "Div Payout%": "35.77%",
    "5Y Div%": "25.58%",
    "Cash Flow %(q)": "+11.27%",
    "Cash Flow %(a)": "+133.75%",
    "Signal": "Buy",
    "Direction": "Strengthening",
    "1M High Date": "2022-04-26"
  },
  {
    "Symbol": "DDS",
    "Name": "Dillard's",
    "Exchange": "NYSE",
    "Last": 307.74,
    "Industry": "Retail - Regional Dept Stores",
    "SIC Description": "SIC-5311 Retail-Department Stores",
    "Time": "10:34 ET",
    "Div Payout%": "35.05%",
    "5Y Div%": "5,507.14%",
    "Cash Flow %(q)": "+75.81%",
    "Cash Flow %(a)": "+406.04%",
    "Signal": "Buy",
    "Direction": "Strengthening",
    "1M High Date": "2022-04-28"
  },
  {
    "Symbol": "FCFS",
    "Name": "Firstcash Holdings Inc",
    "Exchange": "NASDAQ",
    "Last": 78.06,
    "Industry": "Financial Transaction Services",
    "SIC Description": "SIC-5900 Retail-Miscellaneous Retail",
    "Time": "10:35 ET",
    "Div Payout%": "29.40%",
    "5Y Div%": "105.26%",
    "Cash Flow %(q)": "+61.99%",
    "Cash Flow %(a)": "+0.47%",
    "Signal": "Buy",
    "Direction": "Average",
    "1M High Date": "2022-04-29"
  },
  {
    "Symbol": "GCBC",
    "Name": "Greene County Bncp",
    "Exchange": "NASDAQ",
    "Last": 51.9,
    "Industry": "Finance - Savings & Loan",
    "SIC Description": "SIC-6036 Savings Institutions, Not Federally Chartere",
    "Time": "10:32 ET",
    "Div Payout%": "15.11%",
    "5Y Div%": "29.73%",
    "Cash Flow %(q)": "+93.62%",
    "Cash Flow %(a)": "+3.85%",
    "Signal": "Buy",
    "Direction": "Strongest",
    "1M High Date": "2022-04-28"
  },
  {
    "Symbol": "GPK",
    "Name": "Graphic Packaging Holding Company",
    "Exchange": "NYSE",
    "Last": 22.09,
    "Industry": "Containers - Paper Products",
    "SIC Description": "SIC-2650 Paperboard Containers & Boxes",
    "Time": "10:35 ET",
    "Div Payout%": "26.44%",
    "5Y Div%": "30.43%",
    "Cash Flow %(q)": "+32.68%",
    "Cash Flow %(a)": "-26.16%",
    "Signal": "Buy",
    "Direction": "Strongest",
    "1M High Date": "2022-04-29"
  },
  {
    "Symbol": "JNJ",
    "Name": "Johnson & Johnson",
    "Exchange": "NYSE",
    "Last": 180.8,
    "Industry": "Large Cap Pharma",
    "SIC Description": "SIC-2834 Pharmaceutical Preparations",
    "Time": "10:35 ET",
    "Div Payout%": "42.27%",
    "5Y Div%": "33.02%",
    "Cash Flow %(q)": "+32.42%",
    "Cash Flow %(a)": "-0.54%",
    "Signal": "Buy",
    "Direction": "Average",
    "1M High Date": "2022-04-25"
  },
  {
    "Symbol": "MRTN",
    "Name": "Marten Transport L",
    "Exchange": "NASDAQ",
    "Last": 17.63,
    "Industry": "Transportation - Truck",
    "SIC Description": "SIC-4213 Trucking (No Local)",
    "Time": "10:32 ET",
    "Div Payout%": "59.42%",
    "5Y Div%": "1,550.00%",
    "Cash Flow %(q)": "+33.84%",
    "Cash Flow %(a)": "-9.70%",
    "Signal": "Buy",
    "Direction": "Average",
    "1M High Date": "2022-04-29"
  },
  {
    "Symbol": "OPOF",
    "Name": "Old Point Finl Cp",
    "Exchange": "NASDAQ",
    "Last": 25.99,
    "Industry": "Banks - Southeast",
    "SIC Description": "SIC-6021 National Commercial Banks",
    "Time": "2022-04-29",
    "Div Payout%": "31.04%",
    "5Y Div%": "25.00%",
    "Cash Flow %(q)": "+31.63%",
    "Cash Flow %(a)": "+368.29%",
    "Signal": "Buy",
    "Direction": "Average",
    "1M High Date": "2022-04-26"
  },
  {
    "Symbol": "ULH",
    "Name": "Universal Logis Holdings",
    "Exchange": "NASDAQ",
    "Last": 20.51,
    "Industry": "Transportation - Services",
    "SIC Description": "SIC-4213 Trucking (No Local)",
    "Time": "10:14 ET",
    "Div Payout%": "13.05%",
    "5Y Div%": "50.00%",
    "Cash Flow %(q)": "+54.94%",
    "Cash Flow %(a)": "-16.17%",
    "Signal": "Buy",
    "Direction": "Average",
    "1M High Date": "2022-04-29"
  },
  {
    "Symbol": "WM",
    "Name": "Waste Management",
    "Exchange": "NYSE",
    "Last": 163.02,
    "Industry": "Waste Removal Svcs",
    "SIC Description": "SIC-4953 Refuse Systems",
    "Time": "10:35 ET",
    "Div Payout%": "47.21%",
    "5Y Div%": "40.24%",
    "Cash Flow %(q)": "+29.61%",
    "Cash Flow %(a)": "+27.48%",
    "Signal": "Buy",
    "Direction": "Average",
    "1M High Date": "2022-04-28"
  },
  {
    "Symbol": "Downloaded from Barchart.com as of 05-02-2022 09:35am CDT",
    "Name": "",
    "Exchange": "",
    "Last": "",
    "Industry": "",
    "SIC Description": "",
    "Time": "",
    "Div Payout%": "",
    "5Y Div%": "",
    "Cash Flow %(q)": "",
    "Cash Flow %(a)": "",
    "Signal": "",
    "Direction": "",
    "1M High Date": ""
  }
]